ai_chat_domain/__init__.py
ai_chat_domain/domain-ontology/chat-ai-0.1.0.owl
ai_chat_domain/model/AIMPMessageMetaInfo.py
ai_chat_domain/model/AIMPMessageMetaInfo.pyi
ai_chat_domain/model/AcceptAccountInviteAdminRequest.py
ai_chat_domain/model/AcceptAccountInviteAdminRequest.pyi
ai_chat_domain/model/AcceptChatRequest.py
ai_chat_domain/model/AcceptChatRequest.pyi
ai_chat_domain/model/AcceptDeveloperRequest.py
ai_chat_domain/model/AcceptDeveloperRequest.pyi
ai_chat_domain/model/AcceptLoginChangeAdminRequest.py
ai_chat_domain/model/AcceptLoginChangeAdminRequest.pyi
ai_chat_domain/model/AcceptMemberInviteAdminRequest.py
ai_chat_domain/model/AcceptMemberInviteAdminRequest.pyi
ai_chat_domain/model/AcceptOwnerChangeAdminRequest.py
ai_chat_domain/model/AcceptOwnerChangeAdminRequest.pyi
ai_chat_domain/model/AcceptOwnerChangeRequest.py
ai_chat_domain/model/AcceptOwnerChangeRequest.pyi
ai_chat_domain/model/AccountQuotaSyncChatNotification.py
ai_chat_domain/model/AccountQuotaSyncChatNotification.pyi
ai_chat_domain/model/AddAccountAdminRequest.py
ai_chat_domain/model/AddAccountAdminRequest.pyi
ai_chat_domain/model/AddAccountLoginAdminRequest.py
ai_chat_domain/model/AddAccountLoginAdminRequest.pyi
ai_chat_domain/model/AddAccountOpportunityAdminRequest.py
ai_chat_domain/model/AddAccountOpportunityAdminRequest.pyi
ai_chat_domain/model/AddAgentAdminRequest.py
ai_chat_domain/model/AddAgentAdminRequest.pyi
ai_chat_domain/model/AddAgentDeveloperRequest.py
ai_chat_domain/model/AddAgentDeveloperRequest.pyi
ai_chat_domain/model/AddAgentInstanceDeveloperRequest.py
ai_chat_domain/model/AddAgentInstanceDeveloperRequest.pyi
ai_chat_domain/model/AddAppDeveloperRequest.py
ai_chat_domain/model/AddAppDeveloperRequest.pyi
ai_chat_domain/model/AddAssetRequest.py
ai_chat_domain/model/AddAssetRequest.pyi
ai_chat_domain/model/AddChatInteractionRequest.py
ai_chat_domain/model/AddChatInteractionRequest.pyi
ai_chat_domain/model/AddChatKGRequest.py
ai_chat_domain/model/AddChatKGRequest.pyi
vital_ai_chat-0.1.20.dist-info/METADATA
vital_ai_chat-0.1.20.dist-info/WHEEL
vital_ai_chat-0.1.20.dist-info/entry_points.txt
vital_ai_chat-0.1.20.dist-info/top_level.txt
vital_ai_chat-0.1.20.dist-info/RECORD
