Metadata-Version: 2.1
Name: vital-ai-chat
Version: 0.1.20
Summary: VitalSigns chat domain
Home-page: https://github.com/vital-ai/vitalhome-chat
Author: Marc Hadfield
Author-email: marc@vital.ai
License: Apache License 2.0
Classifier: Programming Language :: Python :: 3.10
Classifier: License :: OSI Approved :: Apache Software License
Classifier: Operating System :: OS Independent
Requires-Python: >=3.10
Requires-Dist: vital-ai-vitalsigns>=0.1.22
Requires-Dist: vital-ai-domain>=0.1.7
Requires-Dist: vital-ai-haley>=0.1.8
Requires-Dist: vital-ai-haley-kg>=0.1.20
Requires-Dist: vital-ai-haley-ml>=0.1.6
Requires-Dist: vital-ai-aimp>=0.1.16
